dopamine/__init__.py
dopamine/colab/__init__.py
dopamine/colab/utils.py
dopamine/continuous_domains/__init__.py
dopamine/continuous_domains/run_experiment.py
dopamine/continuous_domains/train.py
dopamine/discrete_domains/__init__.py
dopamine/discrete_domains/atari_lib.py
dopamine/discrete_domains/checkpointer.py
dopamine/discrete_domains/gym_lib.py
dopamine/discrete_domains/iteration_statistics.py
dopamine/discrete_domains/legacy_networks.py
dopamine/discrete_domains/logger.py
dopamine/discrete_domains/run_experiment.py
dopamine/discrete_domains/train.py
dopamine/jax/__init__.py
dopamine/jax/checkpointers.py
dopamine/jax/continuous_networks.py
dopamine/jax/losses.py
dopamine/jax/networks.py
dopamine/jax/serialization.py
dopamine/jax/agents/__init__.py
dopamine/jax/agents/dqn/__init__.py
dopamine/jax/agents/dqn/dqn_agent.py
dopamine/jax/agents/full_rainbow/__init__.py
dopamine/jax/agents/full_rainbow/full_rainbow_agent.py
dopamine/jax/agents/implicit_quantile/__init__.py
dopamine/jax/agents/implicit_quantile/implicit_quantile_agent.py
dopamine/jax/agents/ppo/__init__.py
dopamine/jax/agents/ppo/ppo_agent.py
dopamine/jax/agents/quantile/__init__.py
dopamine/jax/agents/quantile/quantile_agent.py
dopamine/jax/agents/rainbow/__init__.py
dopamine/jax/agents/rainbow/rainbow_agent.py
dopamine/jax/agents/sac/__init__.py
dopamine/jax/agents/sac/sac_agent.py
dopamine/jax/replay_memory/__init__.py
dopamine/jax/replay_memory/accumulator.py
dopamine/jax/replay_memory/elements.py
dopamine/jax/replay_memory/replay_buffer.py
dopamine/jax/replay_memory/samplers.py
dopamine/jax/replay_memory/sum_tree.py
dopamine/labs/__init__.py
dopamine/labs/atari_100k/__init__.py
dopamine/labs/atari_100k/atari_100k_rainbow_agent.py
dopamine/labs/atari_100k/atari_100k_runner.py
dopamine/labs/atari_100k/eval_run_experiment.py
dopamine/labs/atari_100k/normalization_utils.py
dopamine/labs/atari_100k/spr_agent.py
dopamine/labs/atari_100k/spr_networks.py
dopamine/labs/atari_100k/train.py
dopamine_rl-4.1.2.dist-info/AUTHORS
dopamine_rl-4.1.2.dist-info/LICENSE
dopamine_rl-4.1.2.dist-info/METADATA
dopamine_rl-4.1.2.dist-info/WHEEL
dopamine_rl-4.1.2.dist-info/top_level.txt
dopamine_rl-4.1.2.dist-info/RECORD
