Metadata-Version: 2.1
Name: dopamine_rl
Version: 4.1.2
Summary: Dopamine: A framework for flexible Reinforcement Learning research
Home-page: https://github.com/google/dopamine
Author: The Dopamine Team
License: Apache 2.0
Project-URL: Documentation, https://github.com/google/dopamine
Project-URL: Bug Reports, https://github.com/google/dopamine/issues
Project-URL: Source, https://github.com/google/dopamine
Keywords: dopamine,reinforcement,machine,learning,research
Classifier: Development Status :: 4 - Beta
Classifier: Intended Audience :: Developers
Classifier: Intended Audience :: Education
Classifier: Intended Audience :: Science/Research
Classifier: License :: OSI Approved :: Apache Software License
Classifier: Programming Language :: Python :: 3
Classifier: Programming Language :: Python :: 3.5
Classifier: Programming Language :: Python :: 3.6
Classifier: Programming Language :: Python :: 3.7
Classifier: Programming Language :: Python :: 3.8
Classifier: Programming Language :: Python :: 3 :: Only
Classifier: Topic :: Scientific/Engineering
Classifier: Topic :: Scientific/Engineering :: Mathematics
Classifier: Topic :: Scientific/Engineering :: Artificial Intelligence
Classifier: Topic :: Software Development
Classifier: Topic :: Software Development :: Libraries
Classifier: Topic :: Software Development :: Libraries :: Python Modules
Requires-Python: >=3.5,<4
License-File: LICENSE
License-File: AUTHORS
Requires-Dist: tensorflow>=2.2.0
Requires-Dist: gin-config>=0.3.0
Requires-Dist: absl-py>=0.9.0
Requires-Dist: ale-py>=0.10.1
Requires-Dist: opencv-python>=3.4.8.29
Requires-Dist: gym<=0.25.2
Requires-Dist: gymnasium>=1.0.0
Requires-Dist: flax>=0.2.0
Requires-Dist: jax>=0.1.72
Requires-Dist: jaxlib>=0.1.51
Requires-Dist: Pillow>=7.0.0
Requires-Dist: numpy>=1.16.4
Requires-Dist: pygame>=1.9.2
Requires-Dist: pandas>=0.24.2
Requires-Dist: python-snappy>=0.7.3
Requires-Dist: tf-slim>=1.0
Requires-Dist: tensorflow-probability>=0.13.0
Requires-Dist: tf-keras>=2.18.0
Requires-Dist: tqdm>=4.64.1
